ArbMasterPy/Collapse_range_string.py
ArbMasterPy/CreateInboundPlanRequest.xlsx
ArbMasterPy/__init__.py
ArbMasterPy/authorisation.py
ArbMasterPy/automated_arbitrage.py
ArbMasterPy/debug_wrapper.py
ArbMasterPy/export_to_amazon_master_wrapper.py
ArbMasterPy/get_other_row_data.py
ArbMasterPy/import_data_wrapper.py
ArbMasterPy/inventory_data.py
ArbMasterPy/master_to_amazon.py
ArbMasterPy/data/Amazon standard inventory - flat file.xlsm
ArbMasterPy/data/CreateInboundPlanRequest.xlsx
ArbMasterPy/data/__init__.py
Arbitrage_Master_Sheet_Py-0.0.29.dist-info/METADATA
Arbitrage_Master_Sheet_Py-0.0.29.dist-info/WHEEL
Arbitrage_Master_Sheet_Py-0.0.29.dist-info/top_level.txt
Arbitrage_Master_Sheet_Py-0.0.29.dist-info/RECORD
